<0>
    <ip>31.170.22.127</ip>
    <port>1080</port>
    <country>Latvia</country>
    <type>socks4</type>
    <anonymity>High</anonymity>
</0>
<1>
    <ip>98.162.25.4</ip>
    <port>31654</port>
    <country>United States of America</country>
    <type>socks4</type>
    <anonymity>High</anonymity>
</1>
<2>
    <ip>174.77.111.198</ip>
    <port>49547</port>
    <country>United States of America</country>
    <type>socks4</type>
    <anonymity>High</anonymity>
</2>
<3>
    <ip>72.206.181.105</ip>
    <port>64935</port>
    <country>United States of America</country>
    <type>socks4</type>
    <anonymity>High</anonymity>
</3>
<4>
    <ip>70.166.167.38</ip>
    <port>57728</port>
    <country>United States of America</country>
    <type>socks4</type>
    <anonymity>High</anonymity>
</4>
<5>
    <ip>98.162.25.29</ip>
    <port>31679</port>
    <country>United States of America</country>
    <type>socks4</type>
    <anonymity>High</anonymity>
</5>
<6>
    <ip>72.210.252.134</ip>
    <port>46164</port>
    <country>United States of America</country>
    <type>socks4</type>
    <anonymity>High</anonymity>
</6>
<7>
    <ip>72.195.34.35</ip>
    <port>27360</port>
    <country>United States of America</country>
    <type>socks4</type>
    <anonymity>High</anonymity>
</7>
<8>
    <ip>154.205.152.96</ip>
    <port>8080</port>
    <country>South Africa</country>
    <type>socks4</type>
    <anonymity>High</anonymity>
</8>
<9>
    <ip>184.178.172.28</ip>
    <port>15294</port>
    <country>United States of America</country>
    <type>socks4</type>
    <anonymity>High</anonymity>
</9>
<10>
    <ip>184.178.172.25</ip>
    <port>15291</port>
    <country>United States of America</country>
    <type>socks4</type>
    <anonymity>High</anonymity>
</10>
<11>
    <ip>72.195.34.60</ip>
    <port>27391</port>
    <country>United States of America</country>
    <type>socks4</type>
    <anonymity>High</anonymity>
</11>
<12>
    <ip>199.58.185.9</ip>
    <port>4145</port>
    <country>United States of America</country>
    <type>socks4</type>
    <anonymity>High</anonymity>
</12>
<13>
    <ip>98.188.47.150</ip>
    <port>4145</port>
    <country>United States of America</country>
    <type>socks4</type>
    <anonymity>High</anonymity>
</13>
<14>
    <ip>142.54.232.6</ip>
    <port>4145</port>
    <country>United States of America</country>
    <type>socks4</type>
    <anonymity>High</anonymity>
</14>
<15>
    <ip>184.170.245.148</ip>
    <port>4145</port>
    <country>United States of America</country>
    <type>socks4</type>
    <anonymity>High</anonymity>
</15>
<16>
    <ip>72.195.34.58</ip>
    <port>4145</port>
    <country>United States of America</country>
    <type>socks4</type>
    <anonymity>High</anonymity>
</16>
<17>
    <ip>174.64.199.79</ip>
    <port>4145</port>
    <country>United States of America</country>
    <type>socks4</type>
    <anonymity>High</anonymity>
</17>
<18>
    <country>United States of America</country>
    <ip>162.214.201.57</ip>
    <port>47930</port>
    <type>socks4</type>
    <anonymity>elite</anonymity>
</18>
<19>
    <country>Indonesia</country>
    <ip>49.128.176.221</ip>
    <port>10800</port>
    <type>socks4</type>
    <anonymity>elite</anonymity>
</19>
<20>
    <country>United States of America</country>
    <ip>107.180.92.72</ip>
    <port>9301</port>
    <type>socks4</type>
    <anonymity>elite</anonymity>
</20>
<21>
    <country>United States of America</country>
    <ip>50.63.12.101</ip>
    <port>61101</port>
    <type>socks4</type>
    <anonymity>elite</anonymity>
</21>
<22>
    <country>Brazil</country>
    <ip>45.70.206.42</ip>
    <port>4145</port>
    <type>socks4</type>
    <anonymity>elite</anonymity>
</22>
<23>
    <country>United States of America</country>
    <ip>162.241.45.22</ip>
    <port>58705</port>
    <type>socks4</type>
    <anonymity>elite</anonymity>
</23>
<24>
    <country>Singapore</country>
    <ip>157.230.250.185</ip>
    <port>27199</port>
    <type>socks4</type>
    <anonymity>elite</anonymity>
</24>
<25>
    <country>United Kingdom of Great Britain and Northern Ireland</country>
    <ip>139.162.238.184</ip>
    <port>49844</port>
    <type>socks4</type>
    <anonymity>elite</anonymity>
</25>
<26>
    <country>Germany</country>
    <ip>207.180.226.58</ip>
    <port>53447</port>
    <type>socks4</type>
    <anonymity>elite</anonymity>
</26>
<27>
    <country>United States of America</country>
    <ip>142.54.231.38</ip>
    <port>4145</port>
    <type>socks4</type>
    <anonymity>elite</anonymity>
</27>
<28>
    <country>United States of America</country>
    <ip>162.214.90.49</ip>
    <port>33100</port>
    <type>socks4</type>
    <anonymity>elite</anonymity>
</28>
<29>
    <country>Canada</country>
    <ip>45.138.69.30</ip>
    <port>20000</port>
    <type>socks4</type>
    <anonymity>elite</anonymity>
</29>
<30>
    <country>United States of America</country>
    <ip>159.223.166.21</ip>
    <port>57874</port>
    <type>socks4</type>
    <anonymity>elite</anonymity>
</30>
<31>
    <country>United States of America</country>
    <ip>162.144.79.97</ip>
    <port>37327</port>
    <type>socks4</type>
    <anonymity>elite</anonymity>
</31>
<32>
    <country>Brazil</country>
    <ip>143.202.226.205</ip>
    <port>4145</port>
    <type>socks4</type>
    <anonymity>elite</anonymity>
</32>
<33>
    <country>Indonesia</country>
    <ip>202.154.178.243</ip>
    <port>5678</port>
    <type>socks4</type>
    <anonymity>elite</anonymity>
</33>
<34>
    <country>Canada</country>
    <ip>104.21.64.208</ip>
    <port>80</port>
    <type>socks4</type>
    <anonymity>elite</anonymity>
</34>
<35>
    <country>Thailand</country>
    <ip>119.42.86.144</ip>
    <port>4145</port>
    <type>socks4</type>
    <anonymity>elite</anonymity>
</35>
<36>
    <country>United States of America</country>
    <ip>147.182.195.54</ip>
    <port>47469</port>
    <type>socks4</type>
    <anonymity>elite</anonymity>
</36>
<37>
    <country>Seychelles</country>
    <ip>197.234.13.11</ip>
    <port>4145</port>
    <type>socks4</type>
    <anonymity>elite</anonymity>
</37>
<38>
    <country>Germany</country>
    <ip>145.239.2.102</ip>
    <port>6266</port>
    <type>socks4</type>
    <anonymity>elite</anonymity>
</38>
<39>
    <country>United States of America</country>
    <ip>50.251.146.121</ip>
    <port>5678</port>
    <type>socks4</type>
    <anonymity>elite</anonymity>
</39>
<40>
    <country>India</country>
    <ip>103.199.97.33</ip>
    <port>39825</port>
    <type>socks4</type>
    <anonymity>elite</anonymity>
</40>
<41>
    <country>India</country>
    <ip>203.115.106.174</ip>
    <port>5678</port>
    <type>socks4</type>
    <anonymity>elite</anonymity>
</41>
<42>
    <country>Singapore</country>
    <ip>148.72.215.79</ip>
    <port>11423</port>
    <type>socks4</type>
    <anonymity>elite</anonymity>
</42>
<43>
    <country>United States of America</country>
    <ip>142.54.239.1</ip>
    <port>4145</port>
    <type>socks4</type>
    <anonymity>elite</anonymity>
</43>
<44>
    <country>United States of America</country>
    <ip>162.240.239.103</ip>
    <port>33594</port>
    <type>socks4</type>
    <anonymity>elite</anonymity>
</44>
<45>
    <country>Brazil</country>
    <ip>45.233.2.1</ip>
    <port>4153</port>
    <type>socks4</type>
    <anonymity>elite</anonymity>
</45>
<46>
    <country>Sweden</country>
    <ip>147.161.188.165</ip>
    <port>10801</port>
    <type>socks4</type>
    <anonymity>elite</anonymity>
</46>
<47>
    <country>Venezuela, Bolivarian Republic of</country>
    <ip>190.205.32.70</ip>
    <port>999</port>
    <type>socks4</type>
    <anonymity>elite</anonymity>
</47>
<48>
    <country>India</country>
    <ip>103.12.246.33</ip>
    <port>4145</port>
    <type>socks4</type>
    <anonymity>elite</anonymity>
</48>
<49>
    <country>Cyprus</country>
    <ip>185.170.233.103</ip>
    <port>47574</port>
    <type>socks4</type>
    <anonymity>elite</anonymity>
</49>
<50>
    <country>Thailand</country>
    <ip>171.5.12.194</ip>
    <port>4145</port>
    <type>socks4</type>
    <anonymity>elite</anonymity>
</50>
<51>
    <country>Kazakhstan</country>
    <ip>31.43.179.214</ip>
    <port>80</port>
    <type>socks4</type>
    <anonymity>elite</anonymity>
</51>
<52>
    <country>Zimbabwe</country>
    <ip>196.44.184.138</ip>
    <port>5678</port>
    <type>socks4</type>
    <anonymity>elite</anonymity>
</52>
<53>
    <country>Brazil</country>
    <ip>177.73.248.26</ip>
    <port>55290</port>
    <type>socks4</type>
    <anonymity>elite</anonymity>
</53>
<54>
    <country>Poland</country>
    <ip>94.154.31.136</ip>
    <port>2114</port>
    <type>socks4</type>
    <anonymity>elite</anonymity>
</54>
<55>
    <country>Cyprus</country>
    <ip>203.22.223.47</ip>
    <port>80</port>
    <type>socks4</type>
    <anonymity>elite</anonymity>
</55>
<56>
    <country>Thailand</country>
    <ip>110.77.161.197</ip>
    <port>4145</port>
    <type>socks4</type>
    <anonymity>elite</anonymity>
</56>
<57>
    <country>Viet Nam</country>
    <ip>171.244.10.204</ip>
    <port>38819</port>
    <type>socks4</type>
    <anonymity>elite</anonymity>
</57>
<58>
    <country>Germany</country>
    <ip>38.242.240.167</ip>
    <port>14871</port>
    <type>socks4</type>
    <anonymity>elite</anonymity>
</58>
<59>
    <country>United States of America</country>
    <ip>38.127.179.194</ip>
    <port>11537</port>
    <type>socks4</type>
    <anonymity>elite</anonymity>
</59>
<60>
    <country>Korea, Republic of</country>
    <ip>121.134.198.156</ip>
    <port>4145</port>
    <type>socks4</type>
    <anonymity>elite</anonymity>
</60>
<61>
    <country>Cambodia</country>
    <ip>36.37.180.59</ip>
    <port>1080</port>
    <type>socks4</type>
    <anonymity>elite</anonymity>
</61>
<62>
    <country>Hong Kong</country>
    <ip>47.242.116.48</ip>
    <port>1080</port>
    <type>socks4</type>
    <anonymity>elite</anonymity>
</62>
<63>
    <country>Thailand</country>
    <ip>49.229.32.173</ip>
    <port>4153</port>
    <type>socks4</type>
    <anonymity>elite</anonymity>
</63>
<64>
    <country>Thailand</country>
    <ip>61.7.184.216</ip>
    <port>4153</port>
    <type>socks4</type>
    <anonymity>elite</anonymity>
</64>
<65>
    <country>Nigeria</country>
    <ip>154.113.161.1</ip>
    <port>5678</port>
    <type>socks4</type>
    <anonymity>elite</anonymity>
</65>
<66>
    <country>Seychelles</country>
    <ip>197.234.13.54</ip>
    <port>4145</port>
    <type>socks4</type>
    <anonymity>elite</anonymity>
</66>
<67>
    <country>United States of America</country>
    <ip>47.254.90.85</ip>
    <port>40392</port>
    <type>socks4</type>
    <anonymity>elite</anonymity>
</67>
<68>
    <country>Germany</country>
    <ip>195.201.19.84</ip>
    <port>443</port>
    <type>socks4</type>
    <anonymity>elite</anonymity>
</68>
<69>
    <country>Kazakhstan</country>
    <ip>164.138.43.14</ip>
    <port>1080</port>
    <type>socks4</type>
    <anonymity>elite</anonymity>
</69>
<70>
    <country>United Kingdom of Great Britain and Northern Ireland</country>
    <ip>45.12.30.170</ip>
    <port>80</port>
    <type>socks4</type>
    <anonymity>elite</anonymity>
</70>
<71>
    <country>South Africa</country>
    <ip>105.29.93.193</ip>
    <port>4145</port>
    <type>socks4</type>
    <anonymity>elite</anonymity>
</71>
<72>
    <country>Indonesia</country>
    <ip>45.112.125.54</ip>
    <port>4145</port>
    <type>socks4</type>
    <anonymity>elite</anonymity>
</72>
<73>
    <country>Brazil</country>
    <ip>201.65.121.66</ip>
    <port>4145</port>
    <type>socks4</type>
    <anonymity>elite</anonymity>
</73>
<74>
    <country>United Kingdom of Great Britain and Northern Ireland</country>
    <ip>45.12.31.104</ip>
    <port>80</port>
    <type>socks4</type>
    <anonymity>elite</anonymity>
</74>
<75>
    <country>Viet Nam</country>
    <ip>113.160.203.118</ip>
    <port>5678</port>
    <type>socks4</type>
    <anonymity>elite</anonymity>
</75>
<76>
    <country>India</country>
    <ip>194.87.140.161</ip>
    <port>1080</port>
    <type>socks4</type>
    <anonymity>elite</anonymity>
</76>
<77>
    <country>Indonesia</country>
    <ip>103.79.96.202</ip>
    <port>4153</port>
    <type>socks4</type>
    <anonymity>elite</anonymity>
</77>
<78>
    <country>China</country>
    <ip>47.100.19.147</ip>
    <port>3129</port>
    <type>socks4</type>
    <anonymity>elite</anonymity>
</78>
<79>
    <country>Japan</country>
    <ip>43.153.174.106</ip>
    <port>443</port>
    <type>socks4</type>
    <anonymity>elite</anonymity>
</79>
<80>
    <country>Türkiye</country>
    <ip>38.41.53.149</ip>
    <port>5678</port>
    <type>socks4</type>
    <anonymity>elite</anonymity>
</80>
<81>
    <country>Thailand</country>
    <ip>116.58.227.73</ip>
    <port>4145</port>
    <type>socks4</type>
    <anonymity>elite</anonymity>
</81>
<82>
    <country>Colombia</country>
    <ip>181.78.13.91</ip>
    <port>5678</port>
    <type>socks4</type>
    <anonymity>elite</anonymity>
</82>
<83>
    <country>Brazil</country>
    <ip>177.125.161.223</ip>
    <port>4145</port>
    <type>socks4</type>
    <anonymity>elite</anonymity>
</83>
<84>
    <country>France</country>
    <ip>213.32.91.205</ip>
    <port>3128</port>
    <type>socks4</type>
    <anonymity>elite</anonymity>
</84>
<85>
    <country>China</country>
    <ip>27.19.223.228</ip>
    <port>44844</port>
    <type>socks4</type>
    <anonymity>elite</anonymity>
</85>
<86>
    <country>Singapore</country>
    <ip>148.66.130.53</ip>
    <port>47011</port>
    <type>socks4</type>
    <anonymity>elite</anonymity>
</86>
<87>
    <country>Russian Federation</country>
    <ip>212.103.118.77</ip>
    <port>5678</port>
    <type>socks4</type>
    <anonymity>elite</anonymity>
</87>
<88>
    <country>Brazil</country>
    <ip>187.62.89.252</ip>
    <port>4153</port>
    <type>socks4</type>
    <anonymity>elite</anonymity>
</88>
<89>
    <country>United States of America</country>
    <ip>192.111.137.35</ip>
    <port>4145</port>
    <type>socks4</type>
    <anonymity>elite</anonymity>
</89>
<90>
    <country>India</country>
    <ip>103.137.45.132</ip>
    <port>55432</port>
    <type>socks4</type>
    <anonymity>elite</anonymity>
</90>
<91>
    <country>China</country>
    <ip>220.249.79.138</ip>
    <port>10109</port>
    <type>socks4</type>
    <anonymity>elite</anonymity>
</91>
<92>
    <country>United States of America</country>
    <ip>162.240.72.139</ip>
    <port>45514</port>
    <type>socks4</type>
    <anonymity>elite</anonymity>
</92>
<93>
    <country>Colombia</country>
    <ip>190.0.22.35</ip>
    <port>61155</port>
    <type>socks4</type>
    <anonymity>elite</anonymity>
</93>
<94>
    <country>Venezuela, Bolivarian Republic of</country>
    <ip>200.8.185.126</ip>
    <port>4145</port>
    <type>socks4</type>
    <anonymity>elite</anonymity>
</94>
<95>
    <country>Indonesia</country>
    <ip>45.112.125.59</ip>
    <port>4145</port>
    <type>socks4</type>
    <anonymity>elite</anonymity>
</95>
<96>
    <country>Chile</country>
    <ip>201.219.156.18</ip>
    <port>5678</port>
    <type>socks4</type>
    <anonymity>elite</anonymity>
</96>
<97>
    <country>Colombia</country>
    <ip>186.145.192.251</ip>
    <port>5678</port>
    <type>socks4</type>
    <anonymity>elite</anonymity>
</97>
<98>
    <country>Bangladesh</country>
    <ip>115.127.75.27</ip>
    <port>7777</port>
    <type>socks4</type>
    <anonymity>elite</anonymity>
</98>
<99>
    <country>United Kingdom of Great Britain and Northern Ireland</country>
    <ip>154.16.63.16</ip>
    <port>443</port>
    <type>socks4</type>
    <anonymity>elite</anonymity>
</99>
<100>
    <country>United States of America</country>
    <ip>174.139.46.100</ip>
    <port>58841</port>
    <type>socks4</type>
    <anonymity>elite</anonymity>
</100>
<101>
    <country>United States of America</country>
    <ip>166.0.235.108</ip>
    <port>40184</port>
    <type>socks4</type>
    <anonymity>elite</anonymity>
</101>
<102>
    <country>India</country>
    <ip>149.129.176.66</ip>
    <port>6666</port>
    <type>socks4</type>
    <anonymity>elite</anonymity>
</102>
<103>
    <country>Indonesia</country>
    <ip>103.79.96.217</ip>
    <port>4153</port>
    <type>socks4</type>
    <anonymity>elite</anonymity>
</103>