<0>
    <country>United States of America</country>
    <ip>216.107.129.135</ip>
    <port>10180</port>
    <type>socks5</type>
    <anonymity>elite</anonymity>
</0>
<1>
    <country>United States of America</country>
    <ip>184.168.146.10</ip>
    <port>31661</port>
    <type>socks5</type>
    <anonymity>elite</anonymity>
</1>
<2>
    <country>Serbia</country>
    <ip>212.200.161.241</ip>
    <port>5678</port>
    <type>socks5</type>
    <anonymity>elite</anonymity>
</2>
<3>
    <country>Brazil</country>
    <ip>138.255.227.5</ip>
    <port>296</port>
    <type>socks5</type>
    <anonymity>elite</anonymity>
</3>
<4>
    <country>Germany</country>
    <ip>138.201.140.125</ip>
    <port>15976</port>
    <type>socks5</type>
    <anonymity>elite</anonymity>
</4>
<5>
    <country>Russian Federation</country>
    <ip>188.92.242.99</ip>
    <port>8088</port>
    <type>socks5</type>
    <anonymity>elite</anonymity>
</5>
<6>
    <country>China</country>
    <ip>124.163.236.54</ip>
    <port>7302</port>
    <type>socks5</type>
    <anonymity>elite</anonymity>
</6>